setup.py
elontools.egg-info/PKG-INFO
elontools.egg-info/SOURCES.txt
elontools.egg-info/dependency_links.txt
elontools.egg-info/entry_points.txt
elontools.egg-info/requires.txt
elontools.egg-info/top_level.txt
image_backup/__init__.py
image_backup/oneplus.py