Metadata-Version: 1.0
Name: elontools
Version: 0.1
Summary: Elon's Tools
Home-page: https://gitee.com/ElonWu/piptool
Author: Elon
Author-email: oneplus@126.com
License: GPL
Keywords: oneplus
Platform: Independant
